datadynamics/__init__.py
datadynamics/environments/__init__.py
datadynamics/environments/collector/__init__.py
datadynamics/environments/collector/collector.py
datadynamics/environments/collector_v0.py
datadynamics/environments/graph_collector/__init__.py
datadynamics/environments/graph_collector/graph_collector.py
datadynamics/environments/graph_collector_v0.py
datadynamics/policies/__init__.py
datadynamics/policies/base_policy/__init__.py
datadynamics/policies/base_policy/base_policy.py
datadynamics/policies/bfs_greedy_policy/__init__.py
datadynamics/policies/bfs_greedy_policy/bfs_greedy_policy.py
datadynamics/policies/bfs_greedy_policy_v0.py
datadynamics/policies/dummy_policy/__init__.py
datadynamics/policies/dummy_policy/dummy_policy.py
datadynamics/policies/dummy_policy_v0.py
datadynamics/policies/greedy_policy/__init__.py
datadynamics/policies/greedy_policy/greedy_policy.py
datadynamics/policies/greedy_policy_v0.py
datadynamics/policies/premade_policy/__init__.py
datadynamics/policies/premade_policy/premade_policy.py
datadynamics/policies/premade_policy_v0.py
datadynamics/policies/random_policy/__init__.py
datadynamics/policies/random_policy/random_policy.py
datadynamics/policies/random_policy_v0.py
datadynamics/utils/__init__.py
datadynamics/utils/colors.py
datadynamics/utils/graph_utils/__init__.py
datadynamics/utils/graph_utils/graph_extractor.py
datadynamics/utils/graph_utils/point_extractor.py
datadynamics/utils/metrics/__init__.py
datadynamics/utils/metrics/otdd.py
datadynamics/utils/objects.py
datadynamics/utils/post_processing/__init__.py
datadynamics/utils/post_processing/extract.py
datadynamics-0.0.1.dist-info/LICENSE
datadynamics-0.0.1.dist-info/METADATA
datadynamics-0.0.1.dist-info/WHEEL
datadynamics-0.0.1.dist-info/RECORD
