Metadata-Version: 2.1
Name: datadynamics
Version: 0.0.1
Summary: Simulation environment for data collection.
Home-page: https://lfwa.github.io/datadynamics/
License: BSD-3-Clause
Author: Lasse F. Wolff Anthony
Author-email: lfwa@proton.me
Requires-Python: >=3.10,<3.12
Classifier: License :: OSI Approved :: BSD License
Classifier: Programming Language :: Python :: 3
Classifier: Programming Language :: Python :: 3.10
Classifier: Programming Language :: Python :: 3.11
Requires-Dist: gymnasium (>=0.27.1,<0.28.0)
Requires-Dist: h5py (>=3.8.0,<4.0.0)
Requires-Dist: matplotlib (>=3.6.3,<4.0.0)
Requires-Dist: networkx[default] (>=3.0,<4.0)
Requires-Dist: numpy (>=1.24.2,<2.0.0)
Requires-Dist: pettingzoo (>=1.22.2,<2.0.0)
Requires-Dist: pillow (>=9.4.0,<10.0.0)
Requires-Dist: pygame (>=2.1.2,<3.0.0)
Requires-Dist: tqdm (>=4.65.0,<5.0.0)
Requires-Dist: vidmaker (>=2.3.0,<3.0.0)
Project-URL: Repository, https://github.com/lfwa/datadynamics
